{
  "version": 1,
  "settings": {
    "layout": {
      "contentSize": "1620px",
      "wideSize": "1830px"
    },
    "color": {
      "palette": [
        {
          "name": "Primary",
          "slug": "primary",
          "color": "#18457B"
        },
        {
          "name": "Secondary",
          "slug": "secondary",
          "color": "#EFEFEF"
        },
        {
          "name": "Border",
          "slug": "border",
          "color": "#5E5A52"
        },
        {
          "name": "Border Dark",
          "slug": "border-dark",
          "color": "#707070"
        },
        {
          "name": "Border dashed",
          "slug": "borderdashed",
          "color": "#C9C9C9"
        },
        {
          "name": "Light",
          "slug": "light",
          "color": "#F7F7F5"
        },
        {
          "name": "Small",
          "slug": "small",
          "color": "#123660"
        },
        {
          "name": "Pagination",
          "slug": "pagination",
          "color": "#1959A4"
        },
        {
          "name": "Price",
          "slug": "price",
          "color": "#54A419"
        }
      ]
    },
    "typography": {
      "fluid": true,
      "fontFamily": {
        "default": "Montserrat, sans-serif"
      },
      "fontSizes": [
        {
          "name": "Small",
          "slug": "small",
          "size": "0.875rem"
        },
        {
          "slug": "regular",
          "name": "Regular",
          "size": "1.5rem"
        },
        {
          "slug": "large",
          "name": "Large",
          "size": "1.125rem"
        },
        {
          "slug": "xl",
          "name": "XL",
          "size": "1.25rem"
        },
        {
          "slug": "xxl",
          "name": "2XL",
          "size": "1.5rem"
        },
        {
          "slug": "xxxl",
          "name": "3XL",
          "size": "1.875rem"
        },
        {
        "size": "3rem",
        "fluidSize": {
          "min": "1.5rem",
          "max": "3rem"
        },
        "slug": "extralarge",
        "name": "Extra Large"
      }
      ]
    }
  },
  "styles": {
    "elements": {
      "link": {
        "typography": {
          "textDecoration": "none"
        }
      }
    }
  }
}
